{
  "name": "Trial by Combat — Theurge Rider",
  "type": "feat",
  "img": "systems/dnd5e/icons/svg/items/feature.svg",
  "system": {
    "activities": {},
    "uses": {
      "spent": 0,
      "recovery": [],
      "max": ""
    },
    "advancement": [],
    "description": {
      "value": "<p>Once per Rage, when you mark a Challenged Foe, you may gain advantage on your next saving throw before the end of your next turn.</p>",
      "chat": ""
    },
    "identifier": "feature-2",
    "source": {
      "revision": 1,
      "rules": "2024"
    },
    "crewed": false,
    "enchant": {},
    "prerequisites": {
      "items": [],
      "repeatable": false,
      "level": null
    },
    "properties": [],
    "requirements": "",
    "type": {
      "value": "",
      "subtype": ""
    }
  },
  "effects": [],
  "folder": "w2aSfMCxvzAP1ely",
  "flags": {"garou": {
      "riderFor": "trialByCombat",
      "auspice": "theurge"
    }
  },
  "_stats": {
    "compendiumSource": "Compendium.garou.garou-features.Item.9oFY2TOnrT74qsRS",
    "duplicateSource": null,
    "exportSource": {
      "worldId": "vindara-5e",
      "uuid": "Item.2sX5jsiTjdevyyXu",
      "coreVersion": "13.351",
      "systemId": "dnd5e",
      "systemVersion": "5.2.5"
    },
    "coreVersion": "13.351",
    "systemId": "dnd5e",
    "systemVersion": "5.2.5",
    "createdTime": 1770050360536,
    "modifiedTime": 1770051151289,
    "lastModifiedBy": "1MqF4AiaVyJDlXbK"
  },
  "ownership": {
    "default": 0
  }
}