{
  "name": "Breed: Lupus",
  "type": "feat",
  "img": "assets/breed/lupus.png",
  "system": {
    "activities": {},
    "uses": {
      "spent": 0,
      "recovery": [],
      "max": ""
    },
    "advancement": [
      {
        "type": "Trait",
        "_id": "6rqPfmfQKXf969tg",
        "configuration": {
          "allowReplacements": false,
          "choices": [
            {
              "count": 1,
              "pool": [
                "skills:prc",
                "skills:sur"
              ]
            }
          ],
          "grants": [],
          "mode": "default"
        },
        "level": 1,
        "title": "Lupus Instincts",
        "hint": "Choose one skill reflecting your wolf-born instincts.",
        "value": {}
      }
    ],
    "description": {
      "value": "",
      "chat": ""
    },
    "identifier": "breed-lupus",
    "source": {
      "revision": 1,
      "rules": "2024"
    },
    "crewed": false,
    "enchant": {},
    "prerequisites": {
      "items": [],
      "repeatable": false,
      "level": 1
    },
    "properties": [
      "trait"
    ],
    "requirements": "",
    "type": {
      "value": "race",
      "subtype": ""
    }
  },
  "effects": [
    {
      "name": "Breed: Lupus",
      "img": "systems/dnd5e/icons/svg/items/feature.svg",
      "origin": "Compendium.garou.garou-features.Item.mUoDmp8d5DLXF963",
      "_id": "yADXI5wkYOmMGWpn",
      "type": "base",
      "system": {},
      "changes": [
        {
          "key": "system.attributes.movement.walk",
          "mode": 2,
          "value": "5",
          "priority": 20,
          "fieldName": "Movement Speed (Walk)",
          "fieldDescription": ""
        },
        {
          "key": "flags.dnd5e.skills.prc.adv",
          "mode": 5,
          "value": "1",
          "priority": 20
        }
      ],
      "disabled": false,
      "duration": {
        "startTime": null,
        "combat": null,
        "seconds": null,
        "rounds": null,
        "turns": null,
        "startRound": null,
        "startTurn": null
      },
      "description": "<p>You have advantage on Wisdom (Perception) checks that rely on smell.</p>",
      "tint": "#ffffff",
      "transfer": true,
      "statuses": [],
      "sort": 0,
      "flags": {
        "dnd5e": {
          "riders": {
            "statuses": []
          }
        }
      },
      "_stats": {
        "compendiumSource": null,
        "duplicateSource": null,
        "exportSource": null,
        "coreVersion": "13.351",
        "systemId": "dnd5e",
        "systemVersion": "5.2.5",
        "lastModifiedBy": null
      }
    }
  ],
  "folder": "0xaIORSsUyifhTeM",
  "flags": {},
  "_stats": {
    "compendiumSource": null,
    "duplicateSource": null,
    "exportSource": {
      "worldId": "vindara-5e",
      "uuid": "Item.mUoDmp8d5DLXF963",
      "coreVersion": "13.351",
      "systemId": "dnd5e",
      "systemVersion": "5.2.5"
    },
    "coreVersion": "13.351",
    "systemId": "dnd5e",
    "systemVersion": "5.2.5",
    "createdTime": 1769825231965,
    "modifiedTime": 1770176117980,
    "lastModifiedBy": "1MqF4AiaVyJDlXbK"
  },
  "ownership": {
    "default": 0
  }
}